acace_tokenizer/__init__.py
acace_tokenizer-0.1.1.dist-info/LICENSE
acace_tokenizer-0.1.1.dist-info/METADATA
acace_tokenizer-0.1.1.dist-info/WHEEL
acace_tokenizer-0.1.1.dist-info/RECORD
